carbon/__init__.py
carbon/carbon_order_ui.py
carbon/cpc.py
carbon/order.py
carbon/pair.py
carbon/helpers/__init__.py
carbon/helpers/cryptocompare.py
carbon/helpers/floatint.py
carbon/helpers/fls.py
carbon/helpers/helpers.py
carbon/helpers/pathgenerator.py
carbon/helpers/pathinterpolation.py
carbon/helpers/pdread.py
carbon/helpers/sharedvar.py
carbon/helpers/simulation.py
carbon/helpers/soltest.py
carbon/helpers/stdimports.py
carbon/helpers/strategym.py
carbon/helpers/version.py
carbon/helpers/widgets.py
carbon/routers/__init__.py
carbon/routers/alpha_router.py
carbon/routers/alpha_router_orig.py
carbon/routers/base_router.py
carbon/routers/exact_base_router.py
carbon/routers/exact_router_x0y0n.py
carbon/routers/fast_router.py
carbon/sdk/__init__.py
carbon/sdk/carbonsdk.py
carbon/sdk/carbonsdk0.py
carbon/sdk/sdkbase.py
carbon/sdk/sdktoken.py
carbon/simulators/__init__.py
carbon/simulators/carbon_simulator.py
carbon/simulators/sim_analytics.py
carbon/tests/__init__.py
carbon/tests/backend_tests/__init__.py
carbon/tests/nbtest/__init__.py
carbon/tests/nbtest/test_0000_TestNotebook.py
carbon/tests/nbtest/test_032_Analytics.py
carbon/tests/nbtest/test_033_carbonpair.py
carbon/tests/nbtest/test_034_Liquidity.py
carbon/tests/nbtest/test_035_UsePositions.py
carbon/tests/nbtest/test_036_LiquidityApprox.py
carbon/tests/nbtest/test_038_CarbonPair.py
carbon/tests/nbtest/test_039_Future.py
carbon/tests/nbtest/test_040_PairInSim.py
carbon/tests/nbtest/test_041_DisabledStrategies.py
carbon/tests/nbtest/test_043_SglOrder.py
carbon/tests/nbtest/test_044_MarginalPriceRouting.py
carbon/tests/nbtest/test_045_OrderBook.py
carbon/tests/nbtest/test_048_PartialFullfilment.py
carbon/tests/nbtest/test_050_OrderUI.py
carbon/tests/nbtest/test_051_Trading.py
carbon/tests/nbtest/test_052_Demo73Helpers.py
carbon/tests/nbtest/test_053_MargPandYInt.py
carbon/tests/nbtest/test_054_SharedVar.py
carbon/tests/nbtest/test_055_PathInterpolation.py
carbon/tests/nbtest/test_056_CarbonPair2.py
carbon_simulator-2.4.1.dist-info/LICENSE
carbon_simulator-2.4.1.dist-info/METADATA
carbon_simulator-2.4.1.dist-info/WHEEL
carbon_simulator-2.4.1.dist-info/top_level.txt
carbon_simulator-2.4.1.dist-info/RECORD
