Metadata-Version: 2.1
Name: carbon-simulator
Version: 2.4.1
Summary: Bancor python carbon and carbon library.                      This python package is developed and maintained by Bancor Research.                      It is meant to assist in the design, testing, and validating of Bancor protocol behavior.                 
Home-page: https://github.com/bancorprotocol/carbon-simulator
Author: Bancor Network
Author-email: mike@bancor.network
License: UNKNOWN
Platform: UNKNOWN
Requires-Dist: pandas
Requires-Dist: numpy
Requires-Dist: matplotlib
Requires-Dist: tabulate
Requires-Dist: setuptools
Requires-Dist: pytest
Provides-Extra: complete
